{
    "total": [
        {
            "id": "100037207193452",
            "count": 0
        },
        {
            "id": "100042110392376",
            "count": 0
        },
        {
            "id": "100050474410190",
            "count": 0
        },
        {
            "id": "100059144701966",
            "count": 1
        },
        {
            "id": "100061163045032",
            "count": 0
        },
        {
            "id": "100061610284985",
            "count": 0
        },
        {
            "id": "100063606694588",
            "count": 14
        },
        {
            "id": "100063910658094",
            "count": 9
        },
        {
            "id": "100064145242315",
            "count": 7
        },
        {
            "id": "100064626197124",
            "count": 7
        },
        {
            "id": "100065155268097",
            "count": 16
        },
        {
            "id": "100066976283903",
            "count": 0
        },
        {
            "id": "100067005042898",
            "count": 0
        },
        {
            "id": "100071698005544",
            "count": 0
        },
        {
            "id": "100073592551544",
            "count": 0
        },
        {
            "id": "100075929287593",
            "count": 8
        },
        {
            "id": "100076890594180",
            "count": 8
        },
        {
            "id": "100077055524958",
            "count": 0
        },
        {
            "id": "100078145901524",
            "count": 0
        },
        {
            "id": "100078845670335",
            "count": 4
        },
        {
            "id": "100080334974294",
            "count": 0
        },
        {
            "id": "100080648858657",
            "count": 0
        },
        {
            "id": "100082302767628",
            "count": 17
        },
        {
            "id": "100082679247810",
            "count": 9
        },
        {
            "id": "100082996650256",
            "count": 4
        },
        {
            "id": "100083092406235",
            "count": 0
        },
        {
            "id": "100084808398659",
            "count": 0
        },
        {
            "id": "100085709954256",
            "count": 2
        },
        {
            "id": "100086286180235",
            "count": 69
        }
    ],
    "week": [
        {
            "id": "100037207193452",
            "count": 0
        },
        {
            "id": "100042110392376",
            "count": 0
        },
        {
            "id": "100050474410190",
            "count": 0
        },
        {
            "id": "100059144701966",
            "count": 1
        },
        {
            "id": "100061163045032",
            "count": 0
        },
        {
            "id": "100061610284985",
            "count": 0
        },
        {
            "id": "100063606694588",
            "count": 14
        },
        {
            "id": "100063910658094",
            "count": 9
        },
        {
            "id": "100064145242315",
            "count": 7
        },
        {
            "id": "100064626197124",
            "count": 7
        },
        {
            "id": "100065155268097",
            "count": 16
        },
        {
            "id": "100066976283903",
            "count": 0
        },
        {
            "id": "100067005042898",
            "count": 0
        },
        {
            "id": "100071698005544",
            "count": 0
        },
        {
            "id": "100073592551544",
            "count": 0
        },
        {
            "id": "100075929287593",
            "count": 8
        },
        {
            "id": "100076890594180",
            "count": 8
        },
        {
            "id": "100077055524958",
            "count": 0
        },
        {
            "id": "100078145901524",
            "count": 0
        },
        {
            "id": "100078845670335",
            "count": 4
        },
        {
            "id": "100080334974294",
            "count": 0
        },
        {
            "id": "100080648858657",
            "count": 0
        },
        {
            "id": "100082302767628",
            "count": 17
        },
        {
            "id": "100082679247810",
            "count": 9
        },
        {
            "id": "100082996650256",
            "count": 4
        },
        {
            "id": "100083092406235",
            "count": 0
        },
        {
            "id": "100084808398659",
            "count": 0
        },
        {
            "id": "100085709954256",
            "count": 2
        },
        {
            "id": "100086286180235",
            "count": 69
        }
    ],
    "day": [
        {
            "id": "100037207193452",
            "count": 0
        },
        {
            "id": "100042110392376",
            "count": 0
        },
        {
            "id": "100050474410190",
            "count": 0
        },
        {
            "id": "100059144701966",
            "count": 1
        },
        {
            "id": "100061163045032",
            "count": 0
        },
        {
            "id": "100061610284985",
            "count": 0
        },
        {
            "id": "100063606694588",
            "count": 14
        },
        {
            "id": "100063910658094",
            "count": 9
        },
        {
            "id": "100064145242315",
            "count": 7
        },
        {
            "id": "100064626197124",
            "count": 7
        },
        {
            "id": "100065155268097",
            "count": 16
        },
        {
            "id": "100066976283903",
            "count": 0
        },
        {
            "id": "100067005042898",
            "count": 0
        },
        {
            "id": "100071698005544",
            "count": 0
        },
        {
            "id": "100073592551544",
            "count": 0
        },
        {
            "id": "100075929287593",
            "count": 8
        },
        {
            "id": "100076890594180",
            "count": 8
        },
        {
            "id": "100077055524958",
            "count": 0
        },
        {
            "id": "100078145901524",
            "count": 0
        },
        {
            "id": "100078845670335",
            "count": 4
        },
        {
            "id": "100080334974294",
            "count": 0
        },
        {
            "id": "100080648858657",
            "count": 0
        },
        {
            "id": "100082302767628",
            "count": 17
        },
        {
            "id": "100082679247810",
            "count": 9
        },
        {
            "id": "100082996650256",
            "count": 4
        },
        {
            "id": "100083092406235",
            "count": 0
        },
        {
            "id": "100084808398659",
            "count": 0
        },
        {
            "id": "100085709954256",
            "count": 2
        },
        {
            "id": "100086286180235",
            "count": 69
        }
    ],
    "time": 4
}