{
    "total": [
        {
            "id": "100001468455803",
            "count": 56
        },
        {
            "id": "100051867972150",
            "count": 131
        },
        {
            "id": "100052191341399",
            "count": 62
        },
        {
            "id": "100075362528303",
            "count": 30
        },
        {
            "id": "100087262068887",
            "count": 0
        },
        {
            "id": "100089307514243",
            "count": 96
        }
    ],
    "week": [
        {
            "id": "100001468455803",
            "count": 56
        },
        {
            "id": "100051867972150",
            "count": 131
        },
        {
            "id": "100052191341399",
            "count": 62
        },
        {
            "id": "100075362528303",
            "count": 30
        },
        {
            "id": "100087262068887",
            "count": 0
        },
        {
            "id": "100089307514243",
            "count": 96
        }
    ],
    "day": [
        {
            "id": "100001468455803",
            "count": 56
        },
        {
            "id": "100051867972150",
            "count": 131
        },
        {
            "id": "100052191341399",
            "count": 62
        },
        {
            "id": "100075362528303",
            "count": 30
        },
        {
            "id": "100087262068887",
            "count": 0
        },
        {
            "id": "100089307514243",
            "count": 96
        }
    ],
    "time": 4
}