{
    "total": [
        {
            "id": "100009215440500",
            "count": 0
        },
        {
            "id": "100022172322245",
            "count": 142
        },
        {
            "id": "100022560408812",
            "count": 0
        },
        {
            "id": "100027964237737",
            "count": 45
        },
        {
            "id": "100029937014085",
            "count": 0
        },
        {
            "id": "100034224413148",
            "count": 5
        },
        {
            "id": "100034991550161",
            "count": 0
        },
        {
            "id": "100040891112924",
            "count": 0
        },
        {
            "id": "100041694590086",
            "count": 20
        },
        {
            "id": "100045832545036",
            "count": 0
        },
        {
            "id": "100046741216027",
            "count": 0
        },
        {
            "id": "100047790373201",
            "count": 0
        },
        {
            "id": "100048316810411",
            "count": 15
        },
        {
            "id": "100049426200039",
            "count": 46
        },
        {
            "id": "100050185210796",
            "count": 2
        },
        {
            "id": "100051965136384",
            "count": 5
        },
        {
            "id": "100052067227595",
            "count": 0
        },
        {
            "id": "100053128155975",
            "count": 0
        },
        {
            "id": "100054576382906",
            "count": 0
        },
        {
            "id": "100054762102811",
            "count": 0
        },
        {
            "id": "100056140091757",
            "count": 0
        },
        {
            "id": "100057260590865",
            "count": 9
        },
        {
            "id": "100058618105684",
            "count": 0
        },
        {
            "id": "100063584392588",
            "count": 4
        },
        {
            "id": "100065077634432",
            "count": 2
        },
        {
            "id": "100065326151537",
            "count": 0
        },
        {
            "id": "100066874025565",
            "count": 1
        },
        {
            "id": "100067490637165",
            "count": 10
        },
        {
            "id": "100068099906161",
            "count": 0
        },
        {
            "id": "100070451941303",
            "count": 0
        },
        {
            "id": "100070460622441",
            "count": 0
        },
        {
            "id": "100070529452406",
            "count": 0
        },
        {
            "id": "100070677429056",
            "count": 10
        },
        {
            "id": "100071305405949",
            "count": 6
        },
        {
            "id": "100076581005324",
            "count": 1
        },
        {
            "id": "100080432205251",
            "count": 0
        },
        {
            "id": "100083003018476",
            "count": 0
        },
        {
            "id": "100088221702617",
            "count": 10
        },
        {
            "id": "100089307514243",
            "count": 186
        },
        {
            "id": "100089343895377",
            "count": 18
        },
        {
            "id": "100071127820748",
            "count": 28
        },
        {
            "id": "100027863194960",
            "count": 5
        },
        {
            "id": "100053406967048",
            "count": 26
        }
    ],
    "week": [
        {
            "id": "100009215440500",
            "count": 0
        },
        {
            "id": "100022172322245",
            "count": 142
        },
        {
            "id": "100022560408812",
            "count": 0
        },
        {
            "id": "100027964237737",
            "count": 45
        },
        {
            "id": "100029937014085",
            "count": 0
        },
        {
            "id": "100034224413148",
            "count": 5
        },
        {
            "id": "100034991550161",
            "count": 0
        },
        {
            "id": "100040891112924",
            "count": 0
        },
        {
            "id": "100041694590086",
            "count": 20
        },
        {
            "id": "100045832545036",
            "count": 0
        },
        {
            "id": "100046741216027",
            "count": 0
        },
        {
            "id": "100047790373201",
            "count": 0
        },
        {
            "id": "100048316810411",
            "count": 15
        },
        {
            "id": "100049426200039",
            "count": 46
        },
        {
            "id": "100050185210796",
            "count": 2
        },
        {
            "id": "100051965136384",
            "count": 5
        },
        {
            "id": "100052067227595",
            "count": 0
        },
        {
            "id": "100053128155975",
            "count": 0
        },
        {
            "id": "100054576382906",
            "count": 0
        },
        {
            "id": "100054762102811",
            "count": 0
        },
        {
            "id": "100056140091757",
            "count": 0
        },
        {
            "id": "100057260590865",
            "count": 9
        },
        {
            "id": "100058618105684",
            "count": 0
        },
        {
            "id": "100063584392588",
            "count": 4
        },
        {
            "id": "100065077634432",
            "count": 2
        },
        {
            "id": "100065326151537",
            "count": 0
        },
        {
            "id": "100066874025565",
            "count": 1
        },
        {
            "id": "100067490637165",
            "count": 10
        },
        {
            "id": "100068099906161",
            "count": 0
        },
        {
            "id": "100070451941303",
            "count": 0
        },
        {
            "id": "100070460622441",
            "count": 0
        },
        {
            "id": "100070529452406",
            "count": 0
        },
        {
            "id": "100070677429056",
            "count": 10
        },
        {
            "id": "100071305405949",
            "count": 6
        },
        {
            "id": "100076581005324",
            "count": 1
        },
        {
            "id": "100080432205251",
            "count": 0
        },
        {
            "id": "100083003018476",
            "count": 0
        },
        {
            "id": "100088221702617",
            "count": 10
        },
        {
            "id": "100089307514243",
            "count": 186
        },
        {
            "id": "100089343895377",
            "count": 18
        },
        {
            "id": "100071127820748",
            "count": 28
        },
        {
            "id": "100027863194960",
            "count": 5
        },
        {
            "id": "100053406967048",
            "count": 26
        }
    ],
    "day": [
        {
            "id": "100009215440500",
            "count": 0
        },
        {
            "id": "100022172322245",
            "count": 142
        },
        {
            "id": "100022560408812",
            "count": 0
        },
        {
            "id": "100027964237737",
            "count": 45
        },
        {
            "id": "100029937014085",
            "count": 0
        },
        {
            "id": "100034224413148",
            "count": 5
        },
        {
            "id": "100034991550161",
            "count": 0
        },
        {
            "id": "100040891112924",
            "count": 0
        },
        {
            "id": "100041694590086",
            "count": 20
        },
        {
            "id": "100045832545036",
            "count": 0
        },
        {
            "id": "100046741216027",
            "count": 0
        },
        {
            "id": "100047790373201",
            "count": 0
        },
        {
            "id": "100048316810411",
            "count": 15
        },
        {
            "id": "100049426200039",
            "count": 46
        },
        {
            "id": "100050185210796",
            "count": 2
        },
        {
            "id": "100051965136384",
            "count": 5
        },
        {
            "id": "100052067227595",
            "count": 0
        },
        {
            "id": "100053128155975",
            "count": 0
        },
        {
            "id": "100054576382906",
            "count": 0
        },
        {
            "id": "100054762102811",
            "count": 0
        },
        {
            "id": "100056140091757",
            "count": 0
        },
        {
            "id": "100057260590865",
            "count": 9
        },
        {
            "id": "100058618105684",
            "count": 0
        },
        {
            "id": "100063584392588",
            "count": 4
        },
        {
            "id": "100065077634432",
            "count": 2
        },
        {
            "id": "100065326151537",
            "count": 0
        },
        {
            "id": "100066874025565",
            "count": 1
        },
        {
            "id": "100067490637165",
            "count": 10
        },
        {
            "id": "100068099906161",
            "count": 0
        },
        {
            "id": "100070451941303",
            "count": 0
        },
        {
            "id": "100070460622441",
            "count": 0
        },
        {
            "id": "100070529452406",
            "count": 0
        },
        {
            "id": "100070677429056",
            "count": 10
        },
        {
            "id": "100071305405949",
            "count": 6
        },
        {
            "id": "100076581005324",
            "count": 1
        },
        {
            "id": "100080432205251",
            "count": 0
        },
        {
            "id": "100083003018476",
            "count": 0
        },
        {
            "id": "100088221702617",
            "count": 10
        },
        {
            "id": "100089307514243",
            "count": 186
        },
        {
            "id": "100089343895377",
            "count": 18
        },
        {
            "id": "100071127820748",
            "count": 28
        },
        {
            "id": "100027863194960",
            "count": 5
        },
        {
            "id": "100053406967048",
            "count": 26
        }
    ],
    "time": 4
}