{
    "total": [
        {
            "id": "666896678",
            "count": 6
        },
        {
            "id": "100012357372733",
            "count": 0
        },
        {
            "id": "100013650934258",
            "count": 0
        },
        {
            "id": "100020448191704",
            "count": 17
        },
        {
            "id": "100022246091318",
            "count": 0
        },
        {
            "id": "100027910933268",
            "count": 0
        },
        {
            "id": "100028592141904",
            "count": 0
        },
        {
            "id": "100029385855531",
            "count": 14
        },
        {
            "id": "100032196753047",
            "count": 0
        },
        {
            "id": "100033552931920",
            "count": 0
        },
        {
            "id": "100034454406231",
            "count": 0
        },
        {
            "id": "100034685710329",
            "count": 0
        },
        {
            "id": "100034926093128",
            "count": 0
        },
        {
            "id": "100036046658041",
            "count": 38
        },
        {
            "id": "100040887095587",
            "count": 49
        },
        {
            "id": "100041214083012",
            "count": 2
        },
        {
            "id": "100041696663242",
            "count": 0
        },
        {
            "id": "100041951503997",
            "count": 0
        },
        {
            "id": "100043089392676",
            "count": 0
        },
        {
            "id": "100046597740303",
            "count": 0
        },
        {
            "id": "100047506606423",
            "count": 0
        },
        {
            "id": "100048123453180",
            "count": 0
        },
        {
            "id": "100048280100841",
            "count": 0
        },
        {
            "id": "100049720366832",
            "count": 0
        },
        {
            "id": "100051141096611",
            "count": 0
        },
        {
            "id": "100051358131656",
            "count": 0
        },
        {
            "id": "100052764916231",
            "count": 0
        },
        {
            "id": "100053152024800",
            "count": 0
        },
        {
            "id": "100053597494750",
            "count": 7
        },
        {
            "id": "100054208006969",
            "count": 1
        },
        {
            "id": "100054269690881",
            "count": 0
        },
        {
            "id": "100054584626753",
            "count": 0
        },
        {
            "id": "100054722220384",
            "count": 14
        },
        {
            "id": "100055437256387",
            "count": 0
        },
        {
            "id": "100056388775499",
            "count": 0
        },
        {
            "id": "100058383546686",
            "count": 0
        },
        {
            "id": "100059244416742",
            "count": 0
        },
        {
            "id": "100064451003031",
            "count": 0
        },
        {
            "id": "100067949802606",
            "count": 0
        },
        {
            "id": "100068315808445",
            "count": 0
        },
        {
            "id": "100069823627666",
            "count": 0
        },
        {
            "id": "100070638745637",
            "count": 0
        },
        {
            "id": "100071794166163",
            "count": 8
        },
        {
            "id": "100071945364691",
            "count": 0
        },
        {
            "id": "100072542570633",
            "count": 0
        },
        {
            "id": "100073273804628",
            "count": 0
        },
        {
            "id": "100074655581757",
            "count": 1
        },
        {
            "id": "100075310532677",
            "count": 0
        },
        {
            "id": "100075347029459",
            "count": 0
        },
        {
            "id": "100075430659995",
            "count": 0
        },
        {
            "id": "100076474574577",
            "count": 0
        },
        {
            "id": "100078091170094",
            "count": 0
        },
        {
            "id": "100078432278513",
            "count": 1
        },
        {
            "id": "100078524001925",
            "count": 0
        },
        {
            "id": "100078704259603",
            "count": 0
        },
        {
            "id": "100079264007542",
            "count": 0
        },
        {
            "id": "100079896125794",
            "count": 0
        },
        {
            "id": "100080082412182",
            "count": 0
        },
        {
            "id": "100080257975038",
            "count": 0
        },
        {
            "id": "100080455364967",
            "count": 0
        },
        {
            "id": "100081337656005",
            "count": 0
        },
        {
            "id": "100081597768039",
            "count": 0
        },
        {
            "id": "100081902546290",
            "count": 0
        },
        {
            "id": "100082976408662",
            "count": 0
        },
        {
            "id": "100083188730099",
            "count": 0
        },
        {
            "id": "100083592632562",
            "count": 0
        },
        {
            "id": "100084807295806",
            "count": 0
        },
        {
            "id": "100085924960438",
            "count": 0
        },
        {
            "id": "100086171786452",
            "count": 0
        },
        {
            "id": "100086269815577",
            "count": 14
        },
        {
            "id": "100086483557014",
            "count": 0
        },
        {
            "id": "100087744740487",
            "count": 0
        },
        {
            "id": "100088594940791",
            "count": 0
        },
        {
            "id": "100089226697067",
            "count": 0
        },
        {
            "id": "100089421371003",
            "count": 0
        },
        {
            "id": "100090161994137",
            "count": 0
        },
        {
            "id": "100090752765776",
            "count": 0
        },
        {
            "id": "100091938732567",
            "count": 2
        },
        {
            "id": "100092206682839",
            "count": 0
        },
        {
            "id": "100092329435887",
            "count": 0
        },
        {
            "id": "100092583738642",
            "count": 0
        },
        {
            "id": "100092723880087",
            "count": 9
        },
        {
            "id": "100092841010684",
            "count": 0
        },
        {
            "id": "100093419180907",
            "count": 0
        },
        {
            "id": "100093520666474",
            "count": 55
        },
        {
            "id": "100094017439979",
            "count": 4
        }
    ],
    "week": [
        {
            "id": "666896678",
            "count": 6
        },
        {
            "id": "100012357372733",
            "count": 0
        },
        {
            "id": "100013650934258",
            "count": 0
        },
        {
            "id": "100020448191704",
            "count": 17
        },
        {
            "id": "100022246091318",
            "count": 0
        },
        {
            "id": "100027910933268",
            "count": 0
        },
        {
            "id": "100028592141904",
            "count": 0
        },
        {
            "id": "100029385855531",
            "count": 14
        },
        {
            "id": "100032196753047",
            "count": 0
        },
        {
            "id": "100033552931920",
            "count": 0
        },
        {
            "id": "100034454406231",
            "count": 0
        },
        {
            "id": "100034685710329",
            "count": 0
        },
        {
            "id": "100034926093128",
            "count": 0
        },
        {
            "id": "100036046658041",
            "count": 38
        },
        {
            "id": "100040887095587",
            "count": 49
        },
        {
            "id": "100041214083012",
            "count": 2
        },
        {
            "id": "100041696663242",
            "count": 0
        },
        {
            "id": "100041951503997",
            "count": 0
        },
        {
            "id": "100043089392676",
            "count": 0
        },
        {
            "id": "100046597740303",
            "count": 0
        },
        {
            "id": "100047506606423",
            "count": 0
        },
        {
            "id": "100048123453180",
            "count": 0
        },
        {
            "id": "100048280100841",
            "count": 0
        },
        {
            "id": "100049720366832",
            "count": 0
        },
        {
            "id": "100051141096611",
            "count": 0
        },
        {
            "id": "100051358131656",
            "count": 0
        },
        {
            "id": "100052764916231",
            "count": 0
        },
        {
            "id": "100053152024800",
            "count": 0
        },
        {
            "id": "100053597494750",
            "count": 7
        },
        {
            "id": "100054208006969",
            "count": 1
        },
        {
            "id": "100054269690881",
            "count": 0
        },
        {
            "id": "100054584626753",
            "count": 0
        },
        {
            "id": "100054722220384",
            "count": 14
        },
        {
            "id": "100055437256387",
            "count": 0
        },
        {
            "id": "100056388775499",
            "count": 0
        },
        {
            "id": "100058383546686",
            "count": 0
        },
        {
            "id": "100059244416742",
            "count": 0
        },
        {
            "id": "100064451003031",
            "count": 0
        },
        {
            "id": "100067949802606",
            "count": 0
        },
        {
            "id": "100068315808445",
            "count": 0
        },
        {
            "id": "100069823627666",
            "count": 0
        },
        {
            "id": "100070638745637",
            "count": 0
        },
        {
            "id": "100071794166163",
            "count": 8
        },
        {
            "id": "100071945364691",
            "count": 0
        },
        {
            "id": "100072542570633",
            "count": 0
        },
        {
            "id": "100073273804628",
            "count": 0
        },
        {
            "id": "100074655581757",
            "count": 1
        },
        {
            "id": "100075310532677",
            "count": 0
        },
        {
            "id": "100075347029459",
            "count": 0
        },
        {
            "id": "100075430659995",
            "count": 0
        },
        {
            "id": "100076474574577",
            "count": 0
        },
        {
            "id": "100078091170094",
            "count": 0
        },
        {
            "id": "100078432278513",
            "count": 1
        },
        {
            "id": "100078524001925",
            "count": 0
        },
        {
            "id": "100078704259603",
            "count": 0
        },
        {
            "id": "100079264007542",
            "count": 0
        },
        {
            "id": "100079896125794",
            "count": 0
        },
        {
            "id": "100080082412182",
            "count": 0
        },
        {
            "id": "100080257975038",
            "count": 0
        },
        {
            "id": "100080455364967",
            "count": 0
        },
        {
            "id": "100081337656005",
            "count": 0
        },
        {
            "id": "100081597768039",
            "count": 0
        },
        {
            "id": "100081902546290",
            "count": 0
        },
        {
            "id": "100082976408662",
            "count": 0
        },
        {
            "id": "100083188730099",
            "count": 0
        },
        {
            "id": "100083592632562",
            "count": 0
        },
        {
            "id": "100084807295806",
            "count": 0
        },
        {
            "id": "100085924960438",
            "count": 0
        },
        {
            "id": "100086171786452",
            "count": 0
        },
        {
            "id": "100086269815577",
            "count": 14
        },
        {
            "id": "100086483557014",
            "count": 0
        },
        {
            "id": "100087744740487",
            "count": 0
        },
        {
            "id": "100088594940791",
            "count": 0
        },
        {
            "id": "100089226697067",
            "count": 0
        },
        {
            "id": "100089421371003",
            "count": 0
        },
        {
            "id": "100090161994137",
            "count": 0
        },
        {
            "id": "100090752765776",
            "count": 0
        },
        {
            "id": "100091938732567",
            "count": 2
        },
        {
            "id": "100092206682839",
            "count": 0
        },
        {
            "id": "100092329435887",
            "count": 0
        },
        {
            "id": "100092583738642",
            "count": 0
        },
        {
            "id": "100092723880087",
            "count": 9
        },
        {
            "id": "100092841010684",
            "count": 0
        },
        {
            "id": "100093419180907",
            "count": 0
        },
        {
            "id": "100093520666474",
            "count": 55
        },
        {
            "id": "100094017439979",
            "count": 4
        }
    ],
    "day": [
        {
            "id": "666896678",
            "count": 6
        },
        {
            "id": "100012357372733",
            "count": 0
        },
        {
            "id": "100013650934258",
            "count": 0
        },
        {
            "id": "100020448191704",
            "count": 17
        },
        {
            "id": "100022246091318",
            "count": 0
        },
        {
            "id": "100027910933268",
            "count": 0
        },
        {
            "id": "100028592141904",
            "count": 0
        },
        {
            "id": "100029385855531",
            "count": 14
        },
        {
            "id": "100032196753047",
            "count": 0
        },
        {
            "id": "100033552931920",
            "count": 0
        },
        {
            "id": "100034454406231",
            "count": 0
        },
        {
            "id": "100034685710329",
            "count": 0
        },
        {
            "id": "100034926093128",
            "count": 0
        },
        {
            "id": "100036046658041",
            "count": 38
        },
        {
            "id": "100040887095587",
            "count": 49
        },
        {
            "id": "100041214083012",
            "count": 2
        },
        {
            "id": "100041696663242",
            "count": 0
        },
        {
            "id": "100041951503997",
            "count": 0
        },
        {
            "id": "100043089392676",
            "count": 0
        },
        {
            "id": "100046597740303",
            "count": 0
        },
        {
            "id": "100047506606423",
            "count": 0
        },
        {
            "id": "100048123453180",
            "count": 0
        },
        {
            "id": "100048280100841",
            "count": 0
        },
        {
            "id": "100049720366832",
            "count": 0
        },
        {
            "id": "100051141096611",
            "count": 0
        },
        {
            "id": "100051358131656",
            "count": 0
        },
        {
            "id": "100052764916231",
            "count": 0
        },
        {
            "id": "100053152024800",
            "count": 0
        },
        {
            "id": "100053597494750",
            "count": 7
        },
        {
            "id": "100054208006969",
            "count": 1
        },
        {
            "id": "100054269690881",
            "count": 0
        },
        {
            "id": "100054584626753",
            "count": 0
        },
        {
            "id": "100054722220384",
            "count": 14
        },
        {
            "id": "100055437256387",
            "count": 0
        },
        {
            "id": "100056388775499",
            "count": 0
        },
        {
            "id": "100058383546686",
            "count": 0
        },
        {
            "id": "100059244416742",
            "count": 0
        },
        {
            "id": "100064451003031",
            "count": 0
        },
        {
            "id": "100067949802606",
            "count": 0
        },
        {
            "id": "100068315808445",
            "count": 0
        },
        {
            "id": "100069823627666",
            "count": 0
        },
        {
            "id": "100070638745637",
            "count": 0
        },
        {
            "id": "100071794166163",
            "count": 8
        },
        {
            "id": "100071945364691",
            "count": 0
        },
        {
            "id": "100072542570633",
            "count": 0
        },
        {
            "id": "100073273804628",
            "count": 0
        },
        {
            "id": "100074655581757",
            "count": 1
        },
        {
            "id": "100075310532677",
            "count": 0
        },
        {
            "id": "100075347029459",
            "count": 0
        },
        {
            "id": "100075430659995",
            "count": 0
        },
        {
            "id": "100076474574577",
            "count": 0
        },
        {
            "id": "100078091170094",
            "count": 0
        },
        {
            "id": "100078432278513",
            "count": 1
        },
        {
            "id": "100078524001925",
            "count": 0
        },
        {
            "id": "100078704259603",
            "count": 0
        },
        {
            "id": "100079264007542",
            "count": 0
        },
        {
            "id": "100079896125794",
            "count": 0
        },
        {
            "id": "100080082412182",
            "count": 0
        },
        {
            "id": "100080257975038",
            "count": 0
        },
        {
            "id": "100080455364967",
            "count": 0
        },
        {
            "id": "100081337656005",
            "count": 0
        },
        {
            "id": "100081597768039",
            "count": 0
        },
        {
            "id": "100081902546290",
            "count": 0
        },
        {
            "id": "100082976408662",
            "count": 0
        },
        {
            "id": "100083188730099",
            "count": 0
        },
        {
            "id": "100083592632562",
            "count": 0
        },
        {
            "id": "100084807295806",
            "count": 0
        },
        {
            "id": "100085924960438",
            "count": 0
        },
        {
            "id": "100086171786452",
            "count": 0
        },
        {
            "id": "100086269815577",
            "count": 14
        },
        {
            "id": "100086483557014",
            "count": 0
        },
        {
            "id": "100087744740487",
            "count": 0
        },
        {
            "id": "100088594940791",
            "count": 0
        },
        {
            "id": "100089226697067",
            "count": 0
        },
        {
            "id": "100089421371003",
            "count": 0
        },
        {
            "id": "100090161994137",
            "count": 0
        },
        {
            "id": "100090752765776",
            "count": 0
        },
        {
            "id": "100091938732567",
            "count": 2
        },
        {
            "id": "100092206682839",
            "count": 0
        },
        {
            "id": "100092329435887",
            "count": 0
        },
        {
            "id": "100092583738642",
            "count": 0
        },
        {
            "id": "100092723880087",
            "count": 9
        },
        {
            "id": "100092841010684",
            "count": 0
        },
        {
            "id": "100093419180907",
            "count": 0
        },
        {
            "id": "100093520666474",
            "count": 55
        },
        {
            "id": "100094017439979",
            "count": 4
        }
    ],
    "time": 4
}