{
    "total": [
        {
            "id": "100001679488351",
            "count": 0
        },
        {
            "id": "100015409277523",
            "count": 0
        },
        {
            "id": "100018189836500",
            "count": 3
        },
        {
            "id": "100018728716258",
            "count": 0
        },
        {
            "id": "100027282461002",
            "count": 1
        },
        {
            "id": "100040887095587",
            "count": 237
        },
        {
            "id": "100041156970393",
            "count": 0
        },
        {
            "id": "100049173785421",
            "count": 0
        },
        {
            "id": "100052743857923",
            "count": 0
        },
        {
            "id": "100062633202787",
            "count": 1
        },
        {
            "id": "100063983184735",
            "count": 9
        },
        {
            "id": "100068001699840",
            "count": 0
        },
        {
            "id": "100069091017023",
            "count": 147
        },
        {
            "id": "100070461126618",
            "count": 153
        },
        {
            "id": "100072900513635",
            "count": 175
        },
        {
            "id": "100073252671772",
            "count": 0
        },
        {
            "id": "100073442707892",
            "count": 1
        },
        {
            "id": "100073554533504",
            "count": 0
        },
        {
            "id": "100073985298985",
            "count": 25
        },
        {
            "id": "100074054081300",
            "count": 0
        },
        {
            "id": "100074073343938",
            "count": 0
        },
        {
            "id": "100074545969757",
            "count": 0
        },
        {
            "id": "100074582642904",
            "count": 89
        },
        {
            "id": "100075071220853",
            "count": 0
        },
        {
            "id": "100075298482175",
            "count": 0
        },
        {
            "id": "100075839805257",
            "count": 0
        },
        {
            "id": "100076743735263",
            "count": 0
        },
        {
            "id": "100076966549510",
            "count": 7
        },
        {
            "id": "100077501358341",
            "count": 0
        },
        {
            "id": "100077795222041",
            "count": 98
        },
        {
            "id": "100078021133793",
            "count": 0
        },
        {
            "id": "100078677966120",
            "count": 0
        },
        {
            "id": "100078695445403",
            "count": 0
        },
        {
            "id": "100080071320242",
            "count": 42
        },
        {
            "id": "100081020256605",
            "count": 0
        },
        {
            "id": "100081318193749",
            "count": 0
        },
        {
            "id": "100081922326390",
            "count": 0
        },
        {
            "id": "100082264743568",
            "count": 182
        },
        {
            "id": "100082333115418",
            "count": 0
        },
        {
            "id": "100083931942639",
            "count": 0
        },
        {
            "id": "100084287097354",
            "count": 20
        },
        {
            "id": "100084752984155",
            "count": 0
        },
        {
            "id": "100085055568986",
            "count": 0
        },
        {
            "id": "100085056141926",
            "count": 0
        },
        {
            "id": "100085339818111",
            "count": 0
        },
        {
            "id": "100086496517070",
            "count": 0
        },
        {
            "id": "100086548445303",
            "count": 0
        },
        {
            "id": "100087342709718",
            "count": 5
        },
        {
            "id": "100088046868374",
            "count": 0
        },
        {
            "id": "100089012679000",
            "count": 3
        },
        {
            "id": "100051867972150",
            "count": 2
        },
        {
            "id": "100001468455803",
            "count": 61
        },
        {
            "id": "100068901700581",
            "count": 8
        }
    ],
    "week": [
        {
            "id": "100001679488351",
            "count": 0
        },
        {
            "id": "100015409277523",
            "count": 0
        },
        {
            "id": "100018189836500",
            "count": 3
        },
        {
            "id": "100018728716258",
            "count": 0
        },
        {
            "id": "100027282461002",
            "count": 1
        },
        {
            "id": "100040887095587",
            "count": 237
        },
        {
            "id": "100041156970393",
            "count": 0
        },
        {
            "id": "100049173785421",
            "count": 0
        },
        {
            "id": "100052743857923",
            "count": 0
        },
        {
            "id": "100062633202787",
            "count": 1
        },
        {
            "id": "100063983184735",
            "count": 9
        },
        {
            "id": "100068001699840",
            "count": 0
        },
        {
            "id": "100069091017023",
            "count": 147
        },
        {
            "id": "100070461126618",
            "count": 153
        },
        {
            "id": "100072900513635",
            "count": 175
        },
        {
            "id": "100073252671772",
            "count": 0
        },
        {
            "id": "100073442707892",
            "count": 1
        },
        {
            "id": "100073554533504",
            "count": 0
        },
        {
            "id": "100073985298985",
            "count": 25
        },
        {
            "id": "100074054081300",
            "count": 0
        },
        {
            "id": "100074073343938",
            "count": 0
        },
        {
            "id": "100074545969757",
            "count": 0
        },
        {
            "id": "100074582642904",
            "count": 89
        },
        {
            "id": "100075071220853",
            "count": 0
        },
        {
            "id": "100075298482175",
            "count": 0
        },
        {
            "id": "100075839805257",
            "count": 0
        },
        {
            "id": "100076743735263",
            "count": 0
        },
        {
            "id": "100076966549510",
            "count": 7
        },
        {
            "id": "100077501358341",
            "count": 0
        },
        {
            "id": "100077795222041",
            "count": 98
        },
        {
            "id": "100078021133793",
            "count": 0
        },
        {
            "id": "100078677966120",
            "count": 0
        },
        {
            "id": "100078695445403",
            "count": 0
        },
        {
            "id": "100080071320242",
            "count": 42
        },
        {
            "id": "100081020256605",
            "count": 0
        },
        {
            "id": "100081318193749",
            "count": 0
        },
        {
            "id": "100081922326390",
            "count": 0
        },
        {
            "id": "100082264743568",
            "count": 182
        },
        {
            "id": "100082333115418",
            "count": 0
        },
        {
            "id": "100083931942639",
            "count": 0
        },
        {
            "id": "100084287097354",
            "count": 20
        },
        {
            "id": "100084752984155",
            "count": 0
        },
        {
            "id": "100085055568986",
            "count": 0
        },
        {
            "id": "100085056141926",
            "count": 0
        },
        {
            "id": "100085339818111",
            "count": 0
        },
        {
            "id": "100086496517070",
            "count": 0
        },
        {
            "id": "100086548445303",
            "count": 0
        },
        {
            "id": "100087342709718",
            "count": 5
        },
        {
            "id": "100088046868374",
            "count": 0
        },
        {
            "id": "100089012679000",
            "count": 3
        },
        {
            "id": "100051867972150",
            "count": 2
        },
        {
            "id": "100001468455803",
            "count": 61
        },
        {
            "id": "100068901700581",
            "count": 8
        }
    ],
    "day": [
        {
            "id": "100001679488351",
            "count": 0
        },
        {
            "id": "100015409277523",
            "count": 0
        },
        {
            "id": "100018189836500",
            "count": 3
        },
        {
            "id": "100018728716258",
            "count": 0
        },
        {
            "id": "100027282461002",
            "count": 1
        },
        {
            "id": "100040887095587",
            "count": 237
        },
        {
            "id": "100041156970393",
            "count": 0
        },
        {
            "id": "100049173785421",
            "count": 0
        },
        {
            "id": "100052743857923",
            "count": 0
        },
        {
            "id": "100062633202787",
            "count": 1
        },
        {
            "id": "100063983184735",
            "count": 9
        },
        {
            "id": "100068001699840",
            "count": 0
        },
        {
            "id": "100069091017023",
            "count": 147
        },
        {
            "id": "100070461126618",
            "count": 153
        },
        {
            "id": "100072900513635",
            "count": 175
        },
        {
            "id": "100073252671772",
            "count": 0
        },
        {
            "id": "100073442707892",
            "count": 1
        },
        {
            "id": "100073554533504",
            "count": 0
        },
        {
            "id": "100073985298985",
            "count": 25
        },
        {
            "id": "100074054081300",
            "count": 0
        },
        {
            "id": "100074073343938",
            "count": 0
        },
        {
            "id": "100074545969757",
            "count": 0
        },
        {
            "id": "100074582642904",
            "count": 89
        },
        {
            "id": "100075071220853",
            "count": 0
        },
        {
            "id": "100075298482175",
            "count": 0
        },
        {
            "id": "100075839805257",
            "count": 0
        },
        {
            "id": "100076743735263",
            "count": 0
        },
        {
            "id": "100076966549510",
            "count": 7
        },
        {
            "id": "100077501358341",
            "count": 0
        },
        {
            "id": "100077795222041",
            "count": 98
        },
        {
            "id": "100078021133793",
            "count": 0
        },
        {
            "id": "100078677966120",
            "count": 0
        },
        {
            "id": "100078695445403",
            "count": 0
        },
        {
            "id": "100080071320242",
            "count": 42
        },
        {
            "id": "100081020256605",
            "count": 0
        },
        {
            "id": "100081318193749",
            "count": 0
        },
        {
            "id": "100081922326390",
            "count": 0
        },
        {
            "id": "100082264743568",
            "count": 182
        },
        {
            "id": "100082333115418",
            "count": 0
        },
        {
            "id": "100083931942639",
            "count": 0
        },
        {
            "id": "100084287097354",
            "count": 20
        },
        {
            "id": "100084752984155",
            "count": 0
        },
        {
            "id": "100085055568986",
            "count": 0
        },
        {
            "id": "100085056141926",
            "count": 0
        },
        {
            "id": "100085339818111",
            "count": 0
        },
        {
            "id": "100086496517070",
            "count": 0
        },
        {
            "id": "100086548445303",
            "count": 0
        },
        {
            "id": "100087342709718",
            "count": 5
        },
        {
            "id": "100088046868374",
            "count": 0
        },
        {
            "id": "100089012679000",
            "count": 3
        },
        {
            "id": "100051867972150",
            "count": 2
        },
        {
            "id": "100001468455803",
            "count": 61
        },
        {
            "id": "100068901700581",
            "count": 8
        }
    ],
    "time": 4
}